dpview/__init__.py
dpview/browser_automation.py
dpview/dynamic_content.py
dpview/render_tools.py
dpview/ui_components.py
dpview/utils.py
DPview-0.1.dist-info/METADATA
DPview-0.1.dist-info/WHEEL
DPview-0.1.dist-info/top_level.txt
DPview-0.1.dist-info/RECORD
